Workbook
Name Slicer_Region: #N/A
Name Slicer_Years__Invoice_Date: #N/A

Sheet Data
B2: Retailer Dataset
B4: Retailer | C4: Retailer ID | D4: Invoice Date | E4: Region | F4: State | G4: City | H4: Beverage Brand | I4: Price per Unit | J4: Units Sold | K4: Total Sales | L4: Operating Profit | M4: Operating Margin
B5: BevCo | C5: 1185732 | D5: 44562 | E5: Northeast | F5: New York | G5: New York | H5: Coca-Cola | I5: 0.5 | J5: 12000 | K5: 6000 | L5: 3000 | M5: 0.5
B6: BevCo | C6: 1185732 | D6: 44563 | E6: Northeast | F6: New York | G6: New York | H6: Diet Coke | I6: 0.5 | J6: 10000 | K6: 5000 | L6: 1500 | M6: 0.3
B7: BevCo | C7: 1185732 | D7: 44564 | E7: Northeast | F7: New York | G7: New York | H7: Sprite | I7: 0.4 | J7: 10000 | K7: 4000 | L7: 1400 | M7: 0.35
B8: BevCo | C8: 1185732 | D8: 44565 | E8: Northeast | F8: New York | G8: New York | H8: Fanta | I8: 0.45 | J8: 8500 | K8: 3825 | L8: 1338.75 | M8: 0.35
B9: BevCo | C9: 1185732 | D9: 44566 | E9: Northeast | F9: New York | G9: New York | H9: Powerade | I9: 0.6 | J9: 9000 | K9: 5400 | L9: 1620 | M9: 0.3
B10: BevCo | C10: 1185732 | D10: 44567 | E10: Northeast | F10: New York | G10: New York | H10: Dasani Water | I10: 0.5 | J10: 10000 | K10: 5000 | L10: 1250 | M10: 0.25
B11: BevCo | C11: 1185732 | D11: 44568 | E11: Northeast | F11: New York | G11: New York | H11: Coca-Cola | I11: 0.5 | J11: 12500 | K11: 6250 | L11: 3125 | M11: 0.5
B12: BevCo | C12: 1185732 | D12: 44569 | E12: Northeast | F12: New York | G12: New York | H12: Diet Coke | I12: 0.5 | J12: 9000 | K12: 4500 | L12: 1350 | M12: 0.3
B13: BevCo | C13: 1185732 | D13: 44582 | E13: Northeast | F13: New York | G13: New York | H13: Sprite | I13: 0.4 | J13: 9500 | K13: 3800 | L13: 1330 | M13: 0.35
B14: BevCo | C14: 1185732 | D14: 44583 | E14: Northeast | F14: New York | G14: New York | H14: Fanta | I14: 0.45 | J14: 8250 | K14: 3712.5 | L14: 1299.375 | M14: 0.35
B15: BevCo | C15: 1185732 | D15: 44584 | E15: Northeast | F15: New York | G15: New York | H15: Powerade | I15: 0.6 | J15: 9000 | K15: 5400 | L15: 1620 | M15: 0.3
B16: BevCo | C16: 1185732 | D16: 44585 | E16: Northeast | F16: New York | G16: New York | H16: Dasani Water | I16: 0.5 | J16: 10000 | K16: 5000 | L16: 1250 | M16: 0.25
... B9652: BevCo | C9652: 1185732 | D9652: 44979 | E9652: Northeast | F9652: New Hampshire | G9652: Manchester | H9652: Sprite | I9652: 0.29 | J9652: 830 | K9652: 240.7 | L9652: 64.989 | M9652: 0.27

Sheet Analyze
A3: Sum of Total Sales | B3: Sum of Units Sold | C3: Average of Price per Unit | D3: Sum of Operating Profit
A4: 1577051.6 | B4: 3704990 | C4: 0.40278356 | D4: 651268.3
A6: Sum of Total Sales | B6: Column Labels
A7: Row Labels | B7: 2022 | C7: 2023 | D7: Grand Total
A8: Coca-Cola | B8: 30454.6 | C8: 440281.4 | D8: 470736
A9: Dasani Water | B9: 18117.5 | C9: 327183.3 | D9: 345300.8
A10: Diet Coke | B10: 14351.2 | C10: 247577.7 | D10: 261928.9
A11: Fanta | B11: 7460.4 | C11: 159893.9 | D11: 167354.3
A12: Powerade | B12: 9122.9 | C12: 213255.7 | D12: 222378.6
A13: Sprite | B13: 10885.2 | C13: 188859.6 | D13: 199744.8
A14: Grand Total | B14: 90391.8 | C14: 1577051.6 | D14: 1667443.4
A16: Sum of Total Sales | B16: Column Labels
A17: Row Labels | B17: 2022 | C17: 2023 | D17: Grand Total
A18: Amazon | C18: 206844.8 | D18: 206844.8
A19: BevCo | B19: 81141.5 | C19: 507735.4 | D19: 588876.9
A20: FizzyCo | C20: 321961.6 | D20: 321961.6
A21: Target | B21: 9250.3 | C21: 263886.2 | D21: 273136.5
A22: West Soda | C22: 276623.6 | D22: 276623.6
A23: Grand Total | B23: 90391.8 | C23: 1577051.6 | D23: 1667443.4
A26: Years (Invoice Date) | B26: Quarters (Invoice Date) | C26: Sum of Total Sales | D26: Average of Operating Profit
A27: 2022 | B27: Qtr4 | C27: 90391.8 | D27: 241.15435 | E27: =A27 -> 2022 | F27: =B27 -> Qtr4 | G27: =C27 -> 90391.8 | H27: =D27 -> 241.15435
A28: 2023 | B28: Qtr1 | C28: 383459.1 | D28: 338.11582 | F28: =B28 -> Qtr1 | G28: =C28 -> 383459.1 | H28: =D28 -> 338.11582
B29: Qtr2 | C29: 355718.2 | D29: 327.64214 | F29: =B29 -> Qtr2 | G29: =C29 -> 355718.2 | H29: =D29 -> 327.64214
B30: Qtr3 | C30: 483622 | D30: 413.25352 | F30: =B30 -> Qtr3 | G30: =C30 -> 483622 | H30: =D30 -> 413.25352
B31: Qtr4 | C31: 354252.3 | D31: 447.28746 | E31: =A31 -> 0 | F31: =B31 -> Qtr4 | G31: =C31 -> 354252.3 | H31: =D31 -> 447.28746
A32: Grand Total | C32: 1667443.4 | D32: 366.45007 | F32: =B32 -> 0 | G32: =C32 -> 1667443.4 | H32: =D32 -> 366.45007
F33: =B33 -> 0 | G33: =C33 -> 0 | H33: =D33 -> 0
F34: =B34 -> 0 | G34: =C34 -> 0 | H34: =D34 -> 0

Sheet Dashboard
C11: Sales by Beverage Brand | H11: Sales by Retailer
C12: Brand | D12: Sales 2022 | E12: Sales 2023 | F12: Variance | H12: Brand | I12: Sales 2022 | J12: Sales 2023 | K12: Variance
C13: =Analyze!A8 -> Coca-Cola | D13: =Analyze!B8 -> 30454.6 | E13: =Analyze!C8 -> 440281.4 | F13: =E13-D13 -> 409826.8 | H13: =Analyze!A18 -> Amazon | I13: =Analyze!B18 -> 0 | J13: =Analyze!C18 -> 206844.8 | K13: =J13-I13 -> 206844.8
C14: =Analyze!A9 -> Dasani Water | D14: =Analyze!B9 -> 18117.5 | E14: =Analyze!C9 -> 327183.3 | F14: =E14-D14 -> 309065.8 | H14: =Analyze!A19 -> BevCo | I14: =Analyze!B19 -> 81141.5 | J14: =Analyze!C19 -> 507735.4 | K14: =J14-I14 -> 426593.9
C15: =Analyze!A10 -> Diet Coke | D15: =Analyze!B10 -> 14351.2 | E15: =Analyze!C10 -> 247577.7 | F15: =E15-D15 -> 233226.5 | H15: =Analyze!A20 -> FizzyCo | I15: =Analyze!B20 -> 0 | J15: =Analyze!C20 -> 321961.6 | K15: =J15-I15 -> 321961.6
C16: =Analyze!A11 -> Fanta | D16: =Analyze!B11 -> 7460.4 | E16: =Analyze!C11 -> 159893.9 | F16: =E16-D16 -> 152433.5 | H16: =Analyze!A21 -> Target | I16: =Analyze!B21 -> 9250.3 | J16: =Analyze!C21 -> 263886.2 | K16: =J16-I16 -> 254635.9
C17: =Analyze!A12 -> Powerade | D17: =Analyze!B12 -> 9122.9 | E17: =Analyze!C12 -> 213255.7 | F17: =E17-D17 -> 204132.8 | H17: =Analyze!A22 -> West Soda | I17: =Analyze!B22 -> 0 | J17: =Analyze!C22 -> 276623.6 | K17: =J17-I17 -> 276623.6
C18: =Analyze!A13 -> Sprite | D18: =Analyze!B13 -> 10885.2 | E18: =Analyze!C13 -> 188859.6 | F18: =E18-D18 -> 177974.4 | H18: =Analyze!A23 -> Grand Total | I18: =Analyze!B23 -> 90391.8 | J18: =Analyze!C23 -> 1577051.6 | K18: =J18-I18 -> 1486659.8
C19: Total | D19: =SUM(D13:D18) -> 90391.8 | E19: =SUM(E13:E18) -> 1577051.6 | F19: =SUM(F13:F18) -> 1486659.8 | H19: Total | I19: =SUM(I13:I18) -> 180783.6 | J19: =SUM(J13:J18) -> 3154103.2 | K19: =SUM(K13:K18) -> 2973319.6
C22: Sales and Operating Profit Margin by Quarter
